setup.cfg
setup.py
SBG_CWL_validation.egg-info/PKG-INFO
SBG_CWL_validation.egg-info/SOURCES.txt
SBG_CWL_validation.egg-info/dependency_links.txt
SBG_CWL_validation.egg-info/entry_points.txt
SBG_CWL_validation.egg-info/top_level.txt
sbg_json_validation/__init__.py
sbg_json_validation/cwl_validation.py