Metadata-Version: 1.0
Name: SBG-CWL-validation
Version: 0.2.4
Summary: Best practices validation of workflows and tools json files
Home-page: UNKNOWN
Author: Mohamed Marouf
Author-email: mohamed.marouf@sbgenomics.com
License: UNKNOWN
Keywords: json,CWL,validation
Platform: UNKNOWN
